{"4": {"1": {"metrics": {"client_number": 4, "accuracy": 0.1578125}, "command": ""}, "2": {"metrics": {"client_number": 4, "accuracy": 0.19375}, "command": ""}, "3": {"metrics": {"client_number": 4, "accuracy": 0.3875}, "command": ""}, "4": {"metrics": {"client_number": 4, "accuracy": 0.425}, "command": ""}, "5": {"metrics": {"client_number": 4, "accuracy": 0.5171875}, "command": ""}, "6": {"metrics": {"client_number": 4, "accuracy": 0.61875}, "command": ""}, "7": {"metrics": {"client_number": 4, "accuracy": 0.5703125}, "command": ""}, "8": {"metrics": {"client_number": 4, "accuracy": 0.6765625}, "command": ""}, "9": {"metrics": {"client_number": 4, "accuracy": 0.6078125}, "command": ""}, "10": {"metrics": {"client_number": 4, "accuracy": 0.80625}, "command": ""}, "11": {"metrics": {"client_number": 4, "accuracy": 0.5703125}, "command": ""}, "12": {"metrics": {"client_number": 4, "accuracy": 0.8765625}, "command": ""}, "13": {"metrics": {"client_number": 4, "accuracy": 0.596875}, "command": ""}, "14": {"metrics": {"client_number": 4, "accuracy": 0.8609375}, "command": ""}, "15": {"metrics": {"client_number": 4, "accuracy": 0.6328125}, "command": ""}, "16": {"metrics": {"client_number": 4, "accuracy": 0.934375}, "command": ""}, "17": {"metrics": {"client_number": 4, "accuracy": 0.69375}, "command": ""}, "18": {"metrics": {"client_number": 4, "accuracy": 0.915625}, "command": ""}, "19": {"metrics": {"client_number": 4, "accuracy": 0.7046875}, "command": ""}, "20": {"metrics": {"client_number": 4, "accuracy": 0.928125}, "command": ""}, "21": {"metrics": {"client_number": 4, "accuracy": 0.7453125}, "command": ""}, "22": {"metrics": {"client_number": 4, "accuracy": 0.89375}, "command": ""}, "23": {"metrics": {"client_number": 4, "accuracy": 0.7875}, "command": ""}, "24": {"metrics": {"client_number": 4, "accuracy": 0.921875}, "command": ""}, "25": {"metrics": {"client_number": 4, "accuracy": 0.83125}, "command": ""}, "26": {"metrics": {"client_number": 4, "accuracy": 0.896875}, "command": ""}, "27": {"metrics": {"client_number": 4, "accuracy": 0.915625}, "command": ""}, "28": {"metrics": {"client_number": 4, "accuracy": 0.9359375}, "command": ""}, "29": {"metrics": {"client_number": 4, "accuracy": 0.9}, "command": ""}, "30": {"metrics": {"client_number": 4, "accuracy": 0.9296875}, "command": ""}, "31": {"metrics": {"client_number": 4, "accuracy": 0.9171875}, "command": ""}, "32": {"metrics": {"client_number": 4, "accuracy": 0.9140625}, "command": ""}, "33": {"metrics": {"client_number": 4, "accuracy": 0.95}, "command": ""}, "34": {"metrics": {"client_number": 4, "accuracy": 0.9578125}, "command": ""}, "35": {"metrics": {"client_number": 4, "accuracy": 0.9578125}, "command": ""}, "36": {"metrics": {"client_number": 4, "accuracy": 0.9421875}, "command": ""}, "37": {"metrics": {"client_number": 4, "accuracy": 0.9375}, "command": ""}, "38": {"metrics": {"client_number": 4, "accuracy": 0.95}, "command": ""}, "39": {"metrics": {"client_number": 4, "accuracy": 0.953125}, "command": ""}, "40": {"metrics": {"client_number": 4, "accuracy": 0.9484375}, "command": ""}, "41": {"metrics": {"client_number": 4, "accuracy": 0.9625}, "command": ""}, "42": {"metrics": {"client_number": 4, "accuracy": 0.9453125}, "command": ""}, "43": {"metrics": {"client_number": 4, "accuracy": 0.9421875}, "command": ""}, "44": {"metrics": {"client_number": 4, "accuracy": 0.9625}, "command": ""}, "45": {"metrics": {"client_number": 4, "accuracy": 0.9671875}, "command": ""}, "46": {"metrics": {"client_number": 4, "accuracy": 0.9734375}, "command": ""}, "47": {"metrics": {"client_number": 4, "accuracy": 0.965625}, "command": ""}, "48": {"metrics": {"client_number": 4, "accuracy": 0.9484375}, "command": ""}, "49": {"metrics": {"client_number": 4, "accuracy": 0.965625}, "command": ""}, "50": {"metrics": {"client_number": 4, "accuracy": 0.965625}, "command": ""}, "51": {"metrics": {"client_number": 4, "accuracy": 0.9640625}, "command": ""}, "52": {"metrics": {"client_number": 4, "accuracy": 0.9703125}, "command": ""}, "53": {"metrics": {"client_number": 4, "accuracy": 0.98125}, "command": ""}, "54": {"metrics": {"client_number": 4, "accuracy": 0.975}, "command": ""}, "55": {"metrics": {"client_number": 4, "accuracy": 0.9671875}, "command": ""}, "56": {"metrics": {"client_number": 4, "accuracy": 0.975}, "command": ""}, "57": {"metrics": {"client_number": 4, "accuracy": 0.9640625}, "command": ""}, "58": {"metrics": {"client_number": 4, "accuracy": 0.9765625}, "command": ""}, "59": {"metrics": {"client_number": 4, "accuracy": 0.9796875}, "command": ""}, "60": {"metrics": {"client_number": 4, "accuracy": 0.9765625}, "command": ""}, "61": {"metrics": {"client_number": 4, "accuracy": 0.9734375}, "command": ""}, "62": {"metrics": {"client_number": 4, "accuracy": 0.971875}, "command": ""}, "63": {"metrics": {"client_number": 4, "accuracy": 0.9703125}, "command": ""}, "64": {"metrics": {"client_number": 4, "accuracy": 0.9765625}, "command": ""}, "65": {"metrics": {"client_number": 4, "accuracy": 0.978125}, "command": ""}, "66": {"metrics": {"client_number": 4, "accuracy": 0.978125}, "command": ""}, "67": {"metrics": {"client_number": 4, "accuracy": 0.9734375}, "command": ""}, "68": {"metrics": {"client_number": 4, "accuracy": 0.984375}, "command": ""}, "69": {"metrics": {"client_number": 4, "accuracy": 0.9734375}, "command": ""}, "70": {"metrics": {"client_number": 4, "accuracy": 0.978125}, "command": ""}, "71": {"metrics": {"client_number": 4, "accuracy": 0.984375}, "command": ""}, "72": {"metrics": {"client_number": 4, "accuracy": 0.984375}, "command": ""}, "73": {"metrics": {"client_number": 4, "accuracy": 0.978125}, "command": ""}, "74": {"metrics": {"client_number": 4, "accuracy": 0.9765625}, "command": ""}, "75": {"metrics": {"client_number": 4, "accuracy": 0.9859375}, "command": ""}, "76": {"metrics": {"client_number": 4, "accuracy": 0.98125}, "command": ""}, "77": {"metrics": {"client_number": 4, "accuracy": 0.9828125}, "command": ""}, "78": {"metrics": {"client_number": 4, "accuracy": 0.9875}, "command": ""}, "79": {"metrics": {"client_number": 4, "accuracy": 0.9859375}, "command": ""}, "80": {"metrics": {"client_number": 4, "accuracy": 0.9859375}, "command": ""}, "81": {"metrics": {"client_number": 4, "accuracy": 0.9875}, "command": ""}, "82": {"metrics": {"client_number": 4, "accuracy": 0.9875}, "command": ""}, "83": {"metrics": {"client_number": 4, "accuracy": 0.984375}, "command": ""}, "84": {"metrics": {"client_number": 4, "accuracy": 0.9828125}, "command": ""}, "85": {"metrics": {"client_number": 4, "accuracy": 0.9890625}, "command": ""}, "86": {"metrics": {"client_number": 4, "accuracy": 0.9875}, "command": ""}, "87": {"metrics": {"client_number": 4, "accuracy": 0.98125}, "command": ""}, "88": {"metrics": {"client_number": 4, "accuracy": 0.990625}, "command": ""}, "89": {"metrics": {"client_number": 4, "accuracy": 0.9765625}, "command": ""}, "90": {"metrics": {"client_number": 4, "accuracy": 0.990625}, "command": ""}, "91": {"metrics": {"client_number": 4, "accuracy": 0.9875}, "command": ""}, "92": {"metrics": {"client_number": 4, "accuracy": 0.99375}, "command": ""}, "93": {"metrics": {"client_number": 4, "accuracy": 0.9859375}, "command": ""}, "94": {"metrics": {"client_number": 4, "accuracy": 0.990625}, "command": ""}, "95": {"metrics": {"client_number": 4, "accuracy": 0.9796875}, "command": ""}, "96": {"metrics": {"client_number": 4, "accuracy": 0.9796875}, "command": ""}, "97": {"metrics": {"client_number": 4, "accuracy": 0.9875}, "command": ""}, "98": {"metrics": {"client_number": 4, "accuracy": 0.9875}, "command": ""}, "99": {"metrics": {"client_number": 4, "accuracy": 0.9875}, "command": ""}, "100": {"metrics": {"client_number": 4, "accuracy": 0.990625}, "command": ""}}, "1": {"1": {"metrics": {"client_number": 1, "accuracy": 0.2875}, "command": ""}, "2": {"metrics": {"client_number": 1, "accuracy": 0.5734375}, "command": ""}, "3": {"metrics": {"client_number": 1, "accuracy": 0.61875}, "command": ""}, "4": {"metrics": {"client_number": 1, "accuracy": 0.784375}, "command": ""}, "5": {"metrics": {"client_number": 1, "accuracy": 0.8484375}, "command": ""}, "6": {"metrics": {"client_number": 1, "accuracy": 0.846875}, "command": ""}, "7": {"metrics": {"client_number": 1, "accuracy": 0.88125}, "command": ""}, "8": {"metrics": {"client_number": 1, "accuracy": 0.8796875}, "command": ""}, "9": {"metrics": {"client_number": 1, "accuracy": 0.928125}, "command": ""}, "10": {"metrics": {"client_number": 1, "accuracy": 0.896875}, "command": ""}, "11": {"metrics": {"client_number": 1, "accuracy": 0.9421875}, "command": ""}, "12": {"metrics": {"client_number": 1, "accuracy": 0.90625}, "command": ""}, "13": {"metrics": {"client_number": 1, "accuracy": 0.9640625}, "command": ""}, "14": {"metrics": {"client_number": 1, "accuracy": 0.859375}, "command": ""}, "15": {"metrics": {"client_number": 1, "accuracy": 0.9609375}, "command": ""}, "16": {"metrics": {"client_number": 1, "accuracy": 0.878125}, "command": ""}, "17": {"metrics": {"client_number": 1, "accuracy": 0.965625}, "command": ""}, "18": {"metrics": {"client_number": 1, "accuracy": 0.90625}, "command": ""}, "19": {"metrics": {"client_number": 1, "accuracy": 0.94375}, "command": ""}, "20": {"metrics": {"client_number": 1, "accuracy": 0.9046875}, "command": ""}, "21": {"metrics": {"client_number": 1, "accuracy": 0.9671875}, "command": ""}, "22": {"metrics": {"client_number": 1, "accuracy": 0.9390625}, "command": ""}, "23": {"metrics": {"client_number": 1, "accuracy": 0.971875}, "command": ""}, "24": {"metrics": {"client_number": 1, "accuracy": 0.9171875}, "command": ""}, "25": {"metrics": {"client_number": 1, "accuracy": 0.971875}, "command": ""}, "26": {"metrics": {"client_number": 1, "accuracy": 0.965625}, "command": ""}, "27": {"metrics": {"client_number": 1, "accuracy": 0.9734375}, "command": ""}, "28": {"metrics": {"client_number": 1, "accuracy": 0.95}, "command": ""}, "29": {"metrics": {"client_number": 1, "accuracy": 0.9515625}, "command": ""}, "30": {"metrics": {"client_number": 1, "accuracy": 0.9546875}, "command": ""}, "31": {"metrics": {"client_number": 1, "accuracy": 0.9625}, "command": ""}, "32": {"metrics": {"client_number": 1, "accuracy": 0.9546875}, "command": ""}, "33": {"metrics": {"client_number": 1, "accuracy": 0.9625}, "command": ""}, "34": {"metrics": {"client_number": 1, "accuracy": 0.9765625}, "command": ""}, "35": {"metrics": {"client_number": 1, "accuracy": 0.9671875}, "command": ""}, "36": {"metrics": {"client_number": 1, "accuracy": 0.95625}, "command": ""}, "37": {"metrics": {"client_number": 1, "accuracy": 0.9609375}, "command": ""}, "38": {"metrics": {"client_number": 1, "accuracy": 0.9734375}, "command": ""}, "39": {"metrics": {"client_number": 1, "accuracy": 0.9703125}, "command": ""}, "40": {"metrics": {"client_number": 1, "accuracy": 0.9734375}, "command": ""}, "41": {"metrics": {"client_number": 1, "accuracy": 0.9734375}, "command": ""}, "42": {"metrics": {"client_number": 1, "accuracy": 0.975}, "command": ""}, "43": {"metrics": {"client_number": 1, "accuracy": 0.9890625}, "command": ""}, "44": {"metrics": {"client_number": 1, "accuracy": 0.953125}, "command": ""}, "45": {"metrics": {"client_number": 1, "accuracy": 0.96875}, "command": ""}, "46": {"metrics": {"client_number": 1, "accuracy": 0.9703125}, "command": ""}, "47": {"metrics": {"client_number": 1, "accuracy": 0.9765625}, "command": ""}, "48": {"metrics": {"client_number": 1, "accuracy": 0.9703125}, "command": ""}, "49": {"metrics": {"client_number": 1, "accuracy": 0.971875}, "command": ""}, "50": {"metrics": {"client_number": 1, "accuracy": 0.9765625}, "command": ""}, "51": {"metrics": {"client_number": 1, "accuracy": 0.9734375}, "command": ""}, "52": {"metrics": {"client_number": 1, "accuracy": 0.9703125}, "command": ""}, "53": {"metrics": {"client_number": 1, "accuracy": 0.96875}, "command": ""}, "54": {"metrics": {"client_number": 1, "accuracy": 0.984375}, "command": ""}, "55": {"metrics": {"client_number": 1, "accuracy": 0.965625}, "command": ""}, "56": {"metrics": {"client_number": 1, "accuracy": 0.98125}, "command": ""}, "57": {"metrics": {"client_number": 1, "accuracy": 0.9859375}, "command": ""}, "58": {"metrics": {"client_number": 1, "accuracy": 0.9859375}, "command": ""}, "59": {"metrics": {"client_number": 1, "accuracy": 0.98125}, "command": ""}, "60": {"metrics": {"client_number": 1, "accuracy": 0.98125}, "command": ""}, "61": {"metrics": {"client_number": 1, "accuracy": 0.9765625}, "command": ""}, "62": {"metrics": {"client_number": 1, "accuracy": 0.9796875}, "command": ""}, "63": {"metrics": {"client_number": 1, "accuracy": 0.971875}, "command": ""}, "64": {"metrics": {"client_number": 1, "accuracy": 0.9703125}, "command": ""}, "65": {"metrics": {"client_number": 1, "accuracy": 0.978125}, "command": ""}, "66": {"metrics": {"client_number": 1, "accuracy": 0.978125}, "command": ""}, "67": {"metrics": {"client_number": 1, "accuracy": 0.9703125}, "command": ""}, "68": {"metrics": {"client_number": 1, "accuracy": 0.9765625}, "command": ""}, "69": {"metrics": {"client_number": 1, "accuracy": 0.9765625}, "command": ""}, "70": {"metrics": {"client_number": 1, "accuracy": 0.984375}, "command": ""}, "71": {"metrics": {"client_number": 1, "accuracy": 0.96875}, "command": ""}, "72": {"metrics": {"client_number": 1, "accuracy": 0.978125}, "command": ""}, "73": {"metrics": {"client_number": 1, "accuracy": 0.9796875}, "command": ""}, "74": {"metrics": {"client_number": 1, "accuracy": 0.9703125}, "command": ""}, "75": {"metrics": {"client_number": 1, "accuracy": 0.978125}, "command": ""}, "76": {"metrics": {"client_number": 1, "accuracy": 0.984375}, "command": ""}, "77": {"metrics": {"client_number": 1, "accuracy": 0.984375}, "command": ""}, "78": {"metrics": {"client_number": 1, "accuracy": 0.975}, "command": ""}, "79": {"metrics": {"client_number": 1, "accuracy": 0.9765625}, "command": ""}, "80": {"metrics": {"client_number": 1, "accuracy": 0.975}, "command": ""}, "81": {"metrics": {"client_number": 1, "accuracy": 0.984375}, "command": ""}, "82": {"metrics": {"client_number": 1, "accuracy": 0.9765625}, "command": ""}, "83": {"metrics": {"client_number": 1, "accuracy": 0.971875}, "command": ""}, "84": {"metrics": {"client_number": 1, "accuracy": 0.9859375}, "command": ""}, "85": {"metrics": {"client_number": 1, "accuracy": 0.990625}, "command": ""}, "86": {"metrics": {"client_number": 1, "accuracy": 0.990625}, "command": ""}, "87": {"metrics": {"client_number": 1, "accuracy": 0.9796875}, "command": ""}, "88": {"metrics": {"client_number": 1, "accuracy": 0.975}, "command": ""}, "89": {"metrics": {"client_number": 1, "accuracy": 0.984375}, "command": ""}, "90": {"metrics": {"client_number": 1, "accuracy": 0.9765625}, "command": ""}, "91": {"metrics": {"client_number": 1, "accuracy": 0.9921875}, "command": ""}, "92": {"metrics": {"client_number": 1, "accuracy": 0.98125}, "command": ""}, "93": {"metrics": {"client_number": 1, "accuracy": 0.9875}, "command": ""}, "94": {"metrics": {"client_number": 1, "accuracy": 0.98125}, "command": ""}, "95": {"metrics": {"client_number": 1, "accuracy": 0.971875}, "command": ""}, "96": {"metrics": {"client_number": 1, "accuracy": 0.990625}, "command": ""}, "97": {"metrics": {"client_number": 1, "accuracy": 0.990625}, "command": ""}, "98": {"metrics": {"client_number": 1, "accuracy": 0.978125}, "command": ""}, "99": {"metrics": {"client_number": 1, "accuracy": 0.984375}, "command": ""}, "100": {"metrics": {"client_number": 1, "accuracy": 0.978125}, "command": ""}}, "3": {"1": {"metrics": {"client_number": 3, "accuracy": 0.003125}, "command": ""}, "2": {"metrics": {"client_number": 3, "accuracy": 0.2140625}, "command": ""}, "3": {"metrics": {"client_number": 3, "accuracy": 0.2703125}, "command": ""}, "4": {"metrics": {"client_number": 3, "accuracy": 0.6125}, "command": ""}, "5": {"metrics": {"client_number": 3, "accuracy": 0.5640625}, "command": ""}, "6": {"metrics": {"client_number": 3, "accuracy": 0.7625}, "command": ""}, "7": {"metrics": {"client_number": 3, "accuracy": 0.66875}, "command": ""}, "8": {"metrics": {"client_number": 3, "accuracy": 0.771875}, "command": ""}, "9": {"metrics": {"client_number": 3, "accuracy": 0.7015625}, "command": ""}, "10": {"metrics": {"client_number": 3, "accuracy": 0.809375}, "command": ""}, "11": {"metrics": {"client_number": 3, "accuracy": 0.70625}, "command": ""}, "12": {"metrics": {"client_number": 3, "accuracy": 0.8046875}, "command": ""}, "13": {"metrics": {"client_number": 3, "accuracy": 0.68125}, "command": ""}, "14": {"metrics": {"client_number": 3, "accuracy": 0.853125}, "command": ""}, "15": {"metrics": {"client_number": 3, "accuracy": 0.740625}, "command": ""}, "16": {"metrics": {"client_number": 3, "accuracy": 0.8625}, "command": ""}, "17": {"metrics": {"client_number": 3, "accuracy": 0.734375}, "command": ""}, "18": {"metrics": {"client_number": 3, "accuracy": 0.8453125}, "command": ""}, "19": {"metrics": {"client_number": 3, "accuracy": 0.80625}, "command": ""}, "20": {"metrics": {"client_number": 3, "accuracy": 0.8640625}, "command": ""}, "21": {"metrics": {"client_number": 3, "accuracy": 0.8015625}, "command": ""}, "22": {"metrics": {"client_number": 3, "accuracy": 0.8796875}, "command": ""}, "23": {"metrics": {"client_number": 3, "accuracy": 0.79375}, "command": ""}, "24": {"metrics": {"client_number": 3, "accuracy": 0.890625}, "command": ""}, "25": {"metrics": {"client_number": 3, "accuracy": 0.846875}, "command": ""}, "26": {"metrics": {"client_number": 3, "accuracy": 0.8796875}, "command": ""}, "27": {"metrics": {"client_number": 3, "accuracy": 0.871875}, "command": ""}, "28": {"metrics": {"client_number": 3, "accuracy": 0.9234375}, "command": ""}, "29": {"metrics": {"client_number": 3, "accuracy": 0.884375}, "command": ""}, "30": {"metrics": {"client_number": 3, "accuracy": 0.8984375}, "command": ""}, "31": {"metrics": {"client_number": 3, "accuracy": 0.9078125}, "command": ""}, "32": {"metrics": {"client_number": 3, "accuracy": 0.9359375}, "command": ""}, "33": {"metrics": {"client_number": 3, "accuracy": 0.8890625}, "command": ""}, "34": {"metrics": {"client_number": 3, "accuracy": 0.8984375}, "command": ""}, "35": {"metrics": {"client_number": 3, "accuracy": 0.9078125}, "command": ""}, "36": {"metrics": {"client_number": 3, "accuracy": 0.903125}, "command": ""}, "37": {"metrics": {"client_number": 3, "accuracy": 0.9140625}, "command": ""}, "38": {"metrics": {"client_number": 3, "accuracy": 0.93125}, "command": ""}, "39": {"metrics": {"client_number": 3, "accuracy": 0.9296875}, "command": ""}, "40": {"metrics": {"client_number": 3, "accuracy": 0.9328125}, "command": ""}, "41": {"metrics": {"client_number": 3, "accuracy": 0.940625}, "command": ""}, "42": {"metrics": {"client_number": 3, "accuracy": 0.9328125}, "command": ""}, "43": {"metrics": {"client_number": 3, "accuracy": 0.934375}, "command": ""}, "44": {"metrics": {"client_number": 3, "accuracy": 0.95}, "command": ""}, "45": {"metrics": {"client_number": 3, "accuracy": 0.9328125}, "command": ""}, "46": {"metrics": {"client_number": 3, "accuracy": 0.94375}, "command": ""}, "47": {"metrics": {"client_number": 3, "accuracy": 0.946875}, "command": ""}, "48": {"metrics": {"client_number": 3, "accuracy": 0.940625}, "command": ""}, "49": {"metrics": {"client_number": 3, "accuracy": 0.9546875}, "command": ""}, "50": {"metrics": {"client_number": 3, "accuracy": 0.9546875}, "command": ""}, "51": {"metrics": {"client_number": 3, "accuracy": 0.9375}, "command": ""}, "52": {"metrics": {"client_number": 3, "accuracy": 0.9625}, "command": ""}, "53": {"metrics": {"client_number": 3, "accuracy": 0.9578125}, "command": ""}, "54": {"metrics": {"client_number": 3, "accuracy": 0.94375}, "command": ""}, "55": {"metrics": {"client_number": 3, "accuracy": 0.95}, "command": ""}, "56": {"metrics": {"client_number": 3, "accuracy": 0.965625}, "command": ""}, "57": {"metrics": {"client_number": 3, "accuracy": 0.9703125}, "command": ""}, "58": {"metrics": {"client_number": 3, "accuracy": 0.9484375}, "command": ""}, "59": {"metrics": {"client_number": 3, "accuracy": 0.9515625}, "command": ""}, "60": {"metrics": {"client_number": 3, "accuracy": 0.9578125}, "command": ""}, "61": {"metrics": {"client_number": 3, "accuracy": 0.96875}, "command": ""}, "62": {"metrics": {"client_number": 3, "accuracy": 0.940625}, "command": ""}, "63": {"metrics": {"client_number": 3, "accuracy": 0.9546875}, "command": ""}, "64": {"metrics": {"client_number": 3, "accuracy": 0.96875}, "command": ""}, "65": {"metrics": {"client_number": 3, "accuracy": 0.95}, "command": ""}, "66": {"metrics": {"client_number": 3, "accuracy": 0.946875}, "command": ""}, "67": {"metrics": {"client_number": 3, "accuracy": 0.9609375}, "command": ""}, "68": {"metrics": {"client_number": 3, "accuracy": 0.9734375}, "command": ""}, "69": {"metrics": {"client_number": 3, "accuracy": 0.9578125}, "command": ""}, "70": {"metrics": {"client_number": 3, "accuracy": 0.9625}, "command": ""}, "71": {"metrics": {"client_number": 3, "accuracy": 0.9640625}, "command": ""}, "72": {"metrics": {"client_number": 3, "accuracy": 0.9703125}, "command": ""}, "73": {"metrics": {"client_number": 3, "accuracy": 0.9765625}, "command": ""}, "74": {"metrics": {"client_number": 3, "accuracy": 0.959375}, "command": ""}, "75": {"metrics": {"client_number": 3, "accuracy": 0.9796875}, "command": ""}, "76": {"metrics": {"client_number": 3, "accuracy": 0.9703125}, "command": ""}, "77": {"metrics": {"client_number": 3, "accuracy": 0.971875}, "command": ""}, "78": {"metrics": {"client_number": 3, "accuracy": 0.9859375}, "command": ""}, "79": {"metrics": {"client_number": 3, "accuracy": 0.9734375}, "command": ""}, "80": {"metrics": {"client_number": 3, "accuracy": 0.96875}, "command": ""}, "81": {"metrics": {"client_number": 3, "accuracy": 0.9796875}, "command": ""}, "82": {"metrics": {"client_number": 3, "accuracy": 0.95625}, "command": ""}, "83": {"metrics": {"client_number": 3, "accuracy": 0.9703125}, "command": ""}, "84": {"metrics": {"client_number": 3, "accuracy": 0.9828125}, "command": ""}, "85": {"metrics": {"client_number": 3, "accuracy": 0.9765625}, "command": ""}, "86": {"metrics": {"client_number": 3, "accuracy": 0.9671875}, "command": ""}, "87": {"metrics": {"client_number": 3, "accuracy": 0.978125}, "command": ""}, "88": {"metrics": {"client_number": 3, "accuracy": 0.9703125}, "command": ""}, "89": {"metrics": {"client_number": 3, "accuracy": 0.98125}, "command": ""}, "90": {"metrics": {"client_number": 3, "accuracy": 0.971875}, "command": ""}, "91": {"metrics": {"client_number": 3, "accuracy": 0.9796875}, "command": ""}, "92": {"metrics": {"client_number": 3, "accuracy": 0.975}, "command": ""}, "93": {"metrics": {"client_number": 3, "accuracy": 0.975}, "command": ""}, "94": {"metrics": {"client_number": 3, "accuracy": 0.9703125}, "command": ""}, "95": {"metrics": {"client_number": 3, "accuracy": 0.978125}, "command": ""}, "96": {"metrics": {"client_number": 3, "accuracy": 0.9890625}, "command": ""}, "97": {"metrics": {"client_number": 3, "accuracy": 0.971875}, "command": ""}, "98": {"metrics": {"client_number": 3, "accuracy": 0.98125}, "command": ""}, "99": {"metrics": {"client_number": 3, "accuracy": 0.9828125}, "command": ""}, "100": {"metrics": {"client_number": 3, "accuracy": 0.978125}, "command": ""}}, "0": {"1": {"metrics": {"client_number": 0, "accuracy": 0.4046875, "poisoned_data_accuracy": 0.5390625, "poisoned_data_loss": 0.044527139700949195}, "command": ""}, "2": {"metrics": {"client_number": 0, "accuracy": 0.384375, "poisoned_data_accuracy": 0.434375, "poisoned_data_loss": 0.0762686274945736}, "command": ""}, "3": {"metrics": {"client_number": 0, "accuracy": 0.4046875, "poisoned_data_accuracy": 0.4265625, "poisoned_data_loss": 0.07095791473984718}, "command": ""}, "4": {"metrics": {"client_number": 0, "accuracy": 0.503125, "poisoned_data_accuracy": 0.409375, "poisoned_data_loss": 0.08387033902108669}, "command": ""}, "5": {"metrics": {"client_number": 0, "accuracy": 0.58125, "poisoned_data_accuracy": 0.50625, "poisoned_data_loss": 0.07534502521157264}, "command": ""}, "6": {"metrics": {"client_number": 0, "accuracy": 0.5484375, "poisoned_data_accuracy": 0.3953125, "poisoned_data_loss": 0.09694288969039917}, "command": ""}, "7": {"metrics": {"client_number": 0, "accuracy": 0.66875, "poisoned_data_accuracy": 0.49375, "poisoned_data_loss": 0.07210320383310317}, "command": ""}, "8": {"metrics": {"client_number": 0, "accuracy": 0.63125, "poisoned_data_accuracy": 0.4109375, "poisoned_data_loss": 0.08585245721042156}, "command": ""}, "9": {"metrics": {"client_number": 0, "accuracy": 0.7078125, "poisoned_data_accuracy": 0.55, "poisoned_data_loss": 0.0618774713948369}, "command": ""}, "10": {"metrics": {"client_number": 0, "accuracy": 0.640625, "poisoned_data_accuracy": 0.4328125, "poisoned_data_loss": 0.08886772058904172}, "command": ""}, "11": {"metrics": {"client_number": 0, "accuracy": 0.7859375, "poisoned_data_accuracy": 0.603125, "poisoned_data_loss": 0.04951107390224933}, "command": ""}, "12": {"metrics": {"client_number": 0, "accuracy": 0.640625, "poisoned_data_accuracy": 0.46875, "poisoned_data_loss": 0.08740519694983959}, "command": ""}, "13": {"metrics": {"client_number": 0, "accuracy": 0.8390625, "poisoned_data_accuracy": 0.6515625, "poisoned_data_loss": 0.03837935328483581}, "command": ""}, "14": {"metrics": {"client_number": 0, "accuracy": 0.6, "poisoned_data_accuracy": 0.3328125, "poisoned_data_loss": 0.09745286963880062}, "command": ""}, "15": {"metrics": {"client_number": 0, "accuracy": 0.846875, "poisoned_data_accuracy": 0.653125, "poisoned_data_loss": 0.03705712240189314}, "command": ""}, "16": {"metrics": {"client_number": 0, "accuracy": 0.61875, "poisoned_data_accuracy": 0.3828125, "poisoned_data_loss": 0.09278831221163272}, "command": ""}, "17": {"metrics": {"client_number": 0, "accuracy": 0.8984375, "poisoned_data_accuracy": 0.684375, "poisoned_data_loss": 0.031347925588488576}, "command": ""}, "18": {"metrics": {"client_number": 0, "accuracy": 0.671875, "poisoned_data_accuracy": 0.4140625, "poisoned_data_loss": 0.0821691568940878}, "command": ""}, "19": {"metrics": {"client_number": 0, "accuracy": 0.9421875, "poisoned_data_accuracy": 0.7390625, "poisoned_data_loss": 0.02369322944432497}, "command": ""}, "20": {"metrics": {"client_number": 0, "accuracy": 0.690625, "poisoned_data_accuracy": 0.390625, "poisoned_data_loss": 0.07823618799448014}, "command": ""}, "21": {"metrics": {"client_number": 0, "accuracy": 0.91875, "poisoned_data_accuracy": 0.684375, "poisoned_data_loss": 0.02830879557877779}, "command": ""}, "22": {"metrics": {"client_number": 0, "accuracy": 0.71875, "poisoned_data_accuracy": 0.4890625, "poisoned_data_loss": 0.06584347914904357}, "command": ""}, "23": {"metrics": {"client_number": 0, "accuracy": 0.9484375, "poisoned_data_accuracy": 0.765625, "poisoned_data_loss": 0.021336140390485526}, "command": ""}, "24": {"metrics": {"client_number": 0, "accuracy": 0.7875, "poisoned_data_accuracy": 0.496875, "poisoned_data_loss": 0.05506421886384487}, "command": ""}, "25": {"metrics": {"client_number": 0, "accuracy": 0.9390625, "poisoned_data_accuracy": 0.734375, "poisoned_data_loss": 0.024742714036256074}, "command": ""}, "26": {"metrics": {"client_number": 0, "accuracy": 0.8578125, "poisoned_data_accuracy": 0.60625, "poisoned_data_loss": 0.04111295286566019}, "command": ""}, "27": {"metrics": {"client_number": 0, "accuracy": 0.946875, "poisoned_data_accuracy": 0.7390625, "poisoned_data_loss": 0.02322640847414732}, "command": ""}, "28": {"metrics": {"client_number": 0, "accuracy": 0.91875, "poisoned_data_accuracy": 0.625, "poisoned_data_loss": 0.03393112104386091}, "command": ""}, "29": {"metrics": {"client_number": 0, "accuracy": 0.9296875, "poisoned_data_accuracy": 0.6921875, "poisoned_data_loss": 0.028264968656003475}, "command": ""}, "30": {"metrics": {"client_number": 0, "accuracy": 0.946875, "poisoned_data_accuracy": 0.7, "poisoned_data_loss": 0.02737169824540615}, "command": ""}, "31": {"metrics": {"client_number": 0, "accuracy": 0.9546875, "poisoned_data_accuracy": 0.7359375, "poisoned_data_loss": 0.02293678857386112}, "command": ""}, "32": {"metrics": {"client_number": 0, "accuracy": 0.9734375, "poisoned_data_accuracy": 0.8078125, "poisoned_data_loss": 0.01895816996693611}, "command": ""}, "33": {"metrics": {"client_number": 0, "accuracy": 0.9421875, "poisoned_data_accuracy": 0.753125, "poisoned_data_loss": 0.024623331893235446}, "command": ""}, "34": {"metrics": {"client_number": 0, "accuracy": 0.9796875, "poisoned_data_accuracy": 0.8, "poisoned_data_loss": 0.017491222964599727}, "command": ""}, "35": {"metrics": {"client_number": 0, "accuracy": 0.9671875, "poisoned_data_accuracy": 0.7953125, "poisoned_data_loss": 0.018331774743273854}, "command": ""}, "36": {"metrics": {"client_number": 0, "accuracy": 0.953125, "poisoned_data_accuracy": 0.7671875, "poisoned_data_loss": 0.02048435201868415}, "command": ""}, "37": {"metrics": {"client_number": 0, "accuracy": 0.940625, "poisoned_data_accuracy": 0.75625, "poisoned_data_loss": 0.021167883649468422}, "command": ""}, "38": {"metrics": {"client_number": 0, "accuracy": 0.9484375, "poisoned_data_accuracy": 0.771875, "poisoned_data_loss": 0.020756515581160782}, "command": ""}, "39": {"metrics": {"client_number": 0, "accuracy": 0.965625, "poisoned_data_accuracy": 0.7953125, "poisoned_data_loss": 0.019338945066556333}, "command": ""}, "40": {"metrics": {"client_number": 0, "accuracy": 0.9859375, "poisoned_data_accuracy": 0.8703125, "poisoned_data_loss": 0.013640325842425227}, "command": ""}, "41": {"metrics": {"client_number": 0, "accuracy": 0.978125, "poisoned_data_accuracy": 0.865625, "poisoned_data_loss": 0.013073965208604932}, "command": ""}, "42": {"metrics": {"client_number": 0, "accuracy": 0.9765625, "poisoned_data_accuracy": 0.865625, "poisoned_data_loss": 0.013232706021517516}, "command": ""}, "43": {"metrics": {"client_number": 0, "accuracy": 0.984375, "poisoned_data_accuracy": 0.8734375, "poisoned_data_loss": 0.012325890827924013}, "command": ""}, "44": {"metrics": {"client_number": 0, "accuracy": 0.9828125, "poisoned_data_accuracy": 0.8703125, "poisoned_data_loss": 0.013387619704008102}, "command": ""}, "45": {"metrics": {"client_number": 0, "accuracy": 0.978125, "poisoned_data_accuracy": 0.8375, "poisoned_data_loss": 0.013563995622098446}, "command": ""}, "46": {"metrics": {"client_number": 0, "accuracy": 0.9796875, "poisoned_data_accuracy": 0.8640625, "poisoned_data_loss": 0.013193711126223206}, "command": ""}, "47": {"metrics": {"client_number": 0, "accuracy": 0.9796875, "poisoned_data_accuracy": 0.896875, "poisoned_data_loss": 0.011261648125946521}, "command": ""}, "48": {"metrics": {"client_number": 0, "accuracy": 0.9875, "poisoned_data_accuracy": 0.9265625, "poisoned_data_loss": 0.009168167063035072}, "command": ""}, "49": {"metrics": {"client_number": 0, "accuracy": 0.984375, "poisoned_data_accuracy": 0.8828125, "poisoned_data_loss": 0.01194838173687458}, "command": ""}, "50": {"metrics": {"client_number": 0, "accuracy": 0.9875, "poisoned_data_accuracy": 0.9203125, "poisoned_data_loss": 0.009574165777303278}, "command": ""}, "51": {"metrics": {"client_number": 0, "accuracy": 0.996875, "poisoned_data_accuracy": 0.9078125, "poisoned_data_loss": 0.010647813393734395}, "command": ""}, "52": {"metrics": {"client_number": 0, "accuracy": 0.996875, "poisoned_data_accuracy": 0.90625, "poisoned_data_loss": 0.009568767552264035}, "command": ""}, "53": {"metrics": {"client_number": 0, "accuracy": 0.98125, "poisoned_data_accuracy": 0.8703125, "poisoned_data_loss": 0.012476612837053836}, "command": ""}, "54": {"metrics": {"client_number": 0, "accuracy": 0.9890625, "poisoned_data_accuracy": 0.93125, "poisoned_data_loss": 0.009097167220897973}, "command": ""}, "55": {"metrics": {"client_number": 0, "accuracy": 0.99375, "poisoned_data_accuracy": 0.9421875, "poisoned_data_loss": 0.008299131749663503}, "command": ""}, "56": {"metrics": {"client_number": 0, "accuracy": 0.99375, "poisoned_data_accuracy": 0.940625, "poisoned_data_loss": 0.006188420415855944}, "command": ""}, "57": {"metrics": {"client_number": 0, "accuracy": 0.9703125, "poisoned_data_accuracy": 0.853125, "poisoned_data_loss": 0.013381824688985943}, "command": ""}, "58": {"metrics": {"client_number": 0, "accuracy": 0.996875, "poisoned_data_accuracy": 0.9578125, "poisoned_data_loss": 0.005970933591015637}, "command": ""}, "59": {"metrics": {"client_number": 0, "accuracy": 0.9890625, "poisoned_data_accuracy": 0.9359375, "poisoned_data_loss": 0.006346707278862595}, "command": ""}, "60": {"metrics": {"client_number": 0, "accuracy": 0.99375, "poisoned_data_accuracy": 0.959375, "poisoned_data_loss": 0.0060513396048918365}, "command": ""}, "61": {"metrics": {"client_number": 0, "accuracy": 0.9984375, "poisoned_data_accuracy": 0.959375, "poisoned_data_loss": 0.006428435281850398}, "command": ""}, "62": {"metrics": {"client_number": 0, "accuracy": 0.99375, "poisoned_data_accuracy": 0.9328125, "poisoned_data_loss": 0.0069093683618120846}, "command": ""}, "63": {"metrics": {"client_number": 0, "accuracy": 0.9953125, "poisoned_data_accuracy": 0.9296875, "poisoned_data_loss": 0.0067521278862841426}, "command": ""}, "64": {"metrics": {"client_number": 0, "accuracy": 0.9953125, "poisoned_data_accuracy": 0.9453125, "poisoned_data_loss": 0.00682703034253791}, "command": ""}, "65": {"metrics": {"client_number": 0, "accuracy": 0.990625, "poisoned_data_accuracy": 0.9546875, "poisoned_data_loss": 0.0054829373024404045}, "command": ""}, "66": {"metrics": {"client_number": 0, "accuracy": 0.9984375, "poisoned_data_accuracy": 0.9484375, "poisoned_data_loss": 0.005846560862846672}, "command": ""}, "67": {"metrics": {"client_number": 0, "accuracy": 0.996875, "poisoned_data_accuracy": 0.9421875, "poisoned_data_loss": 0.00609879131661728}, "command": ""}, "68": {"metrics": {"client_number": 0, "accuracy": 0.9953125, "poisoned_data_accuracy": 0.9671875, "poisoned_data_loss": 0.004562717641238123}, "command": ""}, "69": {"metrics": {"client_number": 0, "accuracy": 0.9953125, "poisoned_data_accuracy": 0.9671875, "poisoned_data_loss": 0.0042877882136963304}, "command": ""}, "70": {"metrics": {"client_number": 0, "accuracy": 0.996875, "poisoned_data_accuracy": 0.95, "poisoned_data_loss": 0.005514281569048762}, "command": ""}, "71": {"metrics": {"client_number": 0, "accuracy": 0.9875, "poisoned_data_accuracy": 0.946875, "poisoned_data_loss": 0.0062278883182443675}, "command": ""}, "72": {"metrics": {"client_number": 0, "accuracy": 0.996875, "poisoned_data_accuracy": 0.9828125, "poisoned_data_loss": 0.004342223948333413}, "command": ""}, "73": {"metrics": {"client_number": 0, "accuracy": 0.9984375, "poisoned_data_accuracy": 0.9765625, "poisoned_data_loss": 0.004352644470054656}, "command": ""}, "74": {"metrics": {"client_number": 0, "accuracy": 0.996875, "poisoned_data_accuracy": 0.96875, "poisoned_data_loss": 0.004774635890498757}, "command": ""}, "75": {"metrics": {"client_number": 0, "accuracy": 0.9953125, "poisoned_data_accuracy": 0.9859375, "poisoned_data_loss": 0.003571311547420919}, "command": ""}, "76": {"metrics": {"client_number": 0, "accuracy": 0.99375, "poisoned_data_accuracy": 0.9828125, "poisoned_data_loss": 0.0038085735635831953}, "command": ""}, "77": {"metrics": {"client_number": 0, "accuracy": 0.9984375, "poisoned_data_accuracy": 0.9859375, "poisoned_data_loss": 0.002894448343431577}, "command": ""}, "78": {"metrics": {"client_number": 0, "accuracy": 0.996875, "poisoned_data_accuracy": 0.9703125, "poisoned_data_loss": 0.004386574821546673}, "command": ""}, "79": {"metrics": {"client_number": 0, "accuracy": 1.0, "poisoned_data_accuracy": 0.978125, "poisoned_data_loss": 0.0034652880975045266}, "command": ""}, "80": {"metrics": {"client_number": 0, "accuracy": 0.9953125, "poisoned_data_accuracy": 0.9734375, "poisoned_data_loss": 0.0038810288067907097}, "command": ""}, "81": {"metrics": {"client_number": 0, "accuracy": 0.9984375, "poisoned_data_accuracy": 0.9875, "poisoned_data_loss": 0.002757910918444395}, "command": ""}, "82": {"metrics": {"client_number": 0, "accuracy": 0.9953125, "poisoned_data_accuracy": 0.978125, "poisoned_data_loss": 0.0036783282412216067}, "command": ""}, "83": {"metrics": {"client_number": 0, "accuracy": 0.9921875, "poisoned_data_accuracy": 0.978125, "poisoned_data_loss": 0.0035302744014188646}, "command": ""}, "84": {"metrics": {"client_number": 0, "accuracy": 0.9953125, "poisoned_data_accuracy": 0.996875, "poisoned_data_loss": 0.002596403961069882}, "command": ""}, "85": {"metrics": {"client_number": 0, "accuracy": 0.9953125, "poisoned_data_accuracy": 0.9828125, "poisoned_data_loss": 0.0025864145485684276}, "command": ""}, "86": {"metrics": {"client_number": 0, "accuracy": 0.9984375, "poisoned_data_accuracy": 0.984375, "poisoned_data_loss": 0.002921162318671122}, "command": ""}, "87": {"metrics": {"client_number": 0, "accuracy": 1.0, "poisoned_data_accuracy": 0.9671875, "poisoned_data_loss": 0.004135326715186238}, "command": ""}, "88": {"metrics": {"client_number": 0, "accuracy": 0.996875, "poisoned_data_accuracy": 0.9859375, "poisoned_data_loss": 0.002503468669601716}, "command": ""}, "89": {"metrics": {"client_number": 0, "accuracy": 0.9984375, "poisoned_data_accuracy": 0.9921875, "poisoned_data_loss": 0.002070607396308333}, "command": ""}, "90": {"metrics": {"client_number": 0, "accuracy": 1.0, "poisoned_data_accuracy": 0.9953125, "poisoned_data_loss": 0.0017082488455343991}, "command": ""}, "91": {"metrics": {"client_number": 0, "accuracy": 0.9984375, "poisoned_data_accuracy": 0.9921875, "poisoned_data_loss": 0.0020067331643076614}, "command": ""}, "92": {"metrics": {"client_number": 0, "accuracy": 0.99375, "poisoned_data_accuracy": 0.984375, "poisoned_data_loss": 0.00258476214366965}, "command": ""}, "93": {"metrics": {"client_number": 0, "accuracy": 0.996875, "poisoned_data_accuracy": 0.9765625, "poisoned_data_loss": 0.003108677588170394}, "command": ""}, "94": {"metrics": {"client_number": 0, "accuracy": 0.996875, "poisoned_data_accuracy": 0.9796875, "poisoned_data_loss": 0.002791788277681917}, "command": ""}, "95": {"metrics": {"client_number": 0, "accuracy": 1.0, "poisoned_data_accuracy": 0.9890625, "poisoned_data_loss": 0.002699377998942509}, "command": ""}, "96": {"metrics": {"client_number": 0, "accuracy": 0.996875, "poisoned_data_accuracy": 0.9921875, "poisoned_data_loss": 0.002202088016201742}, "command": ""}, "97": {"metrics": {"client_number": 0, "accuracy": 0.9984375, "poisoned_data_accuracy": 0.990625, "poisoned_data_loss": 0.0018901721894508227}, "command": ""}, "98": {"metrics": {"client_number": 0, "accuracy": 0.996875, "poisoned_data_accuracy": 0.9953125, "poisoned_data_loss": 0.0017163068623631261}, "command": ""}, "99": {"metrics": {"client_number": 0, "accuracy": 0.9953125, "poisoned_data_accuracy": 1.0, "poisoned_data_loss": 0.0013501681067282334}, "command": ""}, "100": {"metrics": {"client_number": 0, "accuracy": 0.996875, "poisoned_data_accuracy": 0.99375, "poisoned_data_loss": 0.0017577117061591708}, "command": ""}}, "2": {"1": {"metrics": {"client_number": 2, "accuracy": 0.2375}, "command": ""}, "2": {"metrics": {"client_number": 2, "accuracy": 0.3890625}, "command": ""}, "3": {"metrics": {"client_number": 2, "accuracy": 0.6625}, "command": ""}, "4": {"metrics": {"client_number": 2, "accuracy": 0.7765625}, "command": ""}, "5": {"metrics": {"client_number": 2, "accuracy": 0.7890625}, "command": ""}, "6": {"metrics": {"client_number": 2, "accuracy": 0.85}, "command": ""}, "7": {"metrics": {"client_number": 2, "accuracy": 0.840625}, "command": ""}, "8": {"metrics": {"client_number": 2, "accuracy": 0.8953125}, "command": ""}, "9": {"metrics": {"client_number": 2, "accuracy": 0.88125}, "command": ""}, "10": {"metrics": {"client_number": 2, "accuracy": 0.9078125}, "command": ""}, "11": {"metrics": {"client_number": 2, "accuracy": 0.865625}, "command": ""}, "12": {"metrics": {"client_number": 2, "accuracy": 0.88125}, "command": ""}, "13": {"metrics": {"client_number": 2, "accuracy": 0.878125}, "command": ""}, "14": {"metrics": {"client_number": 2, "accuracy": 0.9328125}, "command": ""}, "15": {"metrics": {"client_number": 2, "accuracy": 0.840625}, "command": ""}, "16": {"metrics": {"client_number": 2, "accuracy": 0.93125}, "command": ""}, "17": {"metrics": {"client_number": 2, "accuracy": 0.8453125}, "command": ""}, "18": {"metrics": {"client_number": 2, "accuracy": 0.9203125}, "command": ""}, "19": {"metrics": {"client_number": 2, "accuracy": 0.8625}, "command": ""}, "20": {"metrics": {"client_number": 2, "accuracy": 0.925}, "command": ""}, "21": {"metrics": {"client_number": 2, "accuracy": 0.8671875}, "command": ""}, "22": {"metrics": {"client_number": 2, "accuracy": 0.9328125}, "command": ""}, "23": {"metrics": {"client_number": 2, "accuracy": 0.90625}, "command": ""}, "24": {"metrics": {"client_number": 2, "accuracy": 0.93125}, "command": ""}, "25": {"metrics": {"client_number": 2, "accuracy": 0.909375}, "command": ""}, "26": {"metrics": {"client_number": 2, "accuracy": 0.9421875}, "command": ""}, "27": {"metrics": {"client_number": 2, "accuracy": 0.9359375}, "command": ""}, "28": {"metrics": {"client_number": 2, "accuracy": 0.934375}, "command": ""}, "29": {"metrics": {"client_number": 2, "accuracy": 0.95625}, "command": ""}, "30": {"metrics": {"client_number": 2, "accuracy": 0.925}, "command": ""}, "31": {"metrics": {"client_number": 2, "accuracy": 0.9234375}, "command": ""}, "32": {"metrics": {"client_number": 2, "accuracy": 0.940625}, "command": ""}, "33": {"metrics": {"client_number": 2, "accuracy": 0.946875}, "command": ""}, "34": {"metrics": {"client_number": 2, "accuracy": 0.934375}, "command": ""}, "35": {"metrics": {"client_number": 2, "accuracy": 0.9421875}, "command": ""}, "36": {"metrics": {"client_number": 2, "accuracy": 0.9421875}, "command": ""}, "37": {"metrics": {"client_number": 2, "accuracy": 0.9546875}, "command": ""}, "38": {"metrics": {"client_number": 2, "accuracy": 0.934375}, "command": ""}, "39": {"metrics": {"client_number": 2, "accuracy": 0.9390625}, "command": ""}, "40": {"metrics": {"client_number": 2, "accuracy": 0.9375}, "command": ""}, "41": {"metrics": {"client_number": 2, "accuracy": 0.9265625}, "command": ""}, "42": {"metrics": {"client_number": 2, "accuracy": 0.9375}, "command": ""}, "43": {"metrics": {"client_number": 2, "accuracy": 0.9484375}, "command": ""}, "44": {"metrics": {"client_number": 2, "accuracy": 0.971875}, "command": ""}, "45": {"metrics": {"client_number": 2, "accuracy": 0.9375}, "command": ""}, "46": {"metrics": {"client_number": 2, "accuracy": 0.94375}, "command": ""}, "47": {"metrics": {"client_number": 2, "accuracy": 0.9546875}, "command": ""}, "48": {"metrics": {"client_number": 2, "accuracy": 0.9625}, "command": ""}, "49": {"metrics": {"client_number": 2, "accuracy": 0.9578125}, "command": ""}, "50": {"metrics": {"client_number": 2, "accuracy": 0.9515625}, "command": ""}, "51": {"metrics": {"client_number": 2, "accuracy": 0.9515625}, "command": ""}, "52": {"metrics": {"client_number": 2, "accuracy": 0.9640625}, "command": ""}, "53": {"metrics": {"client_number": 2, "accuracy": 0.9546875}, "command": ""}, "54": {"metrics": {"client_number": 2, "accuracy": 0.9609375}, "command": ""}, "55": {"metrics": {"client_number": 2, "accuracy": 0.965625}, "command": ""}, "56": {"metrics": {"client_number": 2, "accuracy": 0.9375}, "command": ""}, "57": {"metrics": {"client_number": 2, "accuracy": 0.959375}, "command": ""}, "58": {"metrics": {"client_number": 2, "accuracy": 0.9453125}, "command": ""}, "59": {"metrics": {"client_number": 2, "accuracy": 0.9734375}, "command": ""}, "60": {"metrics": {"client_number": 2, "accuracy": 0.965625}, "command": ""}, "61": {"metrics": {"client_number": 2, "accuracy": 0.9578125}, "command": ""}, "62": {"metrics": {"client_number": 2, "accuracy": 0.95625}, "command": ""}, "63": {"metrics": {"client_number": 2, "accuracy": 0.9625}, "command": ""}, "64": {"metrics": {"client_number": 2, "accuracy": 0.9671875}, "command": ""}, "65": {"metrics": {"client_number": 2, "accuracy": 0.965625}, "command": ""}, "66": {"metrics": {"client_number": 2, "accuracy": 0.96875}, "command": ""}, "67": {"metrics": {"client_number": 2, "accuracy": 0.965625}, "command": ""}, "68": {"metrics": {"client_number": 2, "accuracy": 0.9609375}, "command": ""}, "69": {"metrics": {"client_number": 2, "accuracy": 0.96875}, "command": ""}, "70": {"metrics": {"client_number": 2, "accuracy": 0.9640625}, "command": ""}, "71": {"metrics": {"client_number": 2, "accuracy": 0.984375}, "command": ""}, "72": {"metrics": {"client_number": 2, "accuracy": 0.9796875}, "command": ""}, "73": {"metrics": {"client_number": 2, "accuracy": 0.96875}, "command": ""}, "74": {"metrics": {"client_number": 2, "accuracy": 0.9609375}, "command": ""}, "75": {"metrics": {"client_number": 2, "accuracy": 0.9703125}, "command": ""}, "76": {"metrics": {"client_number": 2, "accuracy": 0.975}, "command": ""}, "77": {"metrics": {"client_number": 2, "accuracy": 0.965625}, "command": ""}, "78": {"metrics": {"client_number": 2, "accuracy": 0.978125}, "command": ""}, "79": {"metrics": {"client_number": 2, "accuracy": 0.9640625}, "command": ""}, "80": {"metrics": {"client_number": 2, "accuracy": 0.975}, "command": ""}, "81": {"metrics": {"client_number": 2, "accuracy": 0.9703125}, "command": ""}, "82": {"metrics": {"client_number": 2, "accuracy": 0.971875}, "command": ""}, "83": {"metrics": {"client_number": 2, "accuracy": 0.975}, "command": ""}, "84": {"metrics": {"client_number": 2, "accuracy": 0.9609375}, "command": ""}, "85": {"metrics": {"client_number": 2, "accuracy": 0.9828125}, "command": ""}, "86": {"metrics": {"client_number": 2, "accuracy": 0.9765625}, "command": ""}, "87": {"metrics": {"client_number": 2, "accuracy": 0.971875}, "command": ""}, "88": {"metrics": {"client_number": 2, "accuracy": 0.9625}, "command": ""}, "89": {"metrics": {"client_number": 2, "accuracy": 0.975}, "command": ""}, "90": {"metrics": {"client_number": 2, "accuracy": 0.9828125}, "command": ""}, "91": {"metrics": {"client_number": 2, "accuracy": 0.975}, "command": ""}, "92": {"metrics": {"client_number": 2, "accuracy": 0.965625}, "command": ""}, "93": {"metrics": {"client_number": 2, "accuracy": 0.975}, "command": ""}, "94": {"metrics": {"client_number": 2, "accuracy": 0.96875}, "command": ""}, "95": {"metrics": {"client_number": 2, "accuracy": 0.971875}, "command": ""}, "96": {"metrics": {"client_number": 2, "accuracy": 0.9765625}, "command": ""}, "97": {"metrics": {"client_number": 2, "accuracy": 0.9734375}, "command": ""}, "98": {"metrics": {"client_number": 2, "accuracy": 0.9734375}, "command": ""}, "99": {"metrics": {"client_number": 2, "accuracy": 0.978125}, "command": ""}, "100": {"metrics": {"client_number": 2, "accuracy": 0.98125}, "command": ""}}}